{
	"Alligator": {
		"script": "ExtResource( 1 )",
		"item_description": "Alligator mississippiensis",
		"catch_blurb": "See you later- !",
		"item_is_hidden": false,
		"icon": "ExtResource( 2 )",
		"show_item": true,
		"show_scene": false,
		"uses_size": true,
		"action": "",
		"action_params": [],
		"release_action": "",
		"prop_code": "",
		"help_text": "",
		"arm_value": 0.2,
		"hold_offset": 0.0,
		"unselectable": false,
		"category": "fish",
		"alive": true,
		"tier": 2,
		"catch_difficulty": 5.5,
		"catch_speed": 120.0,
		"loot_table": "lake",
		"loot_weight": 0.1,
		"average_size": 250.0,
		"sell_value": 90,
		"obtain_xp": 125,
		"generate_worth": true,
		"can_be_sold": true,
		"show_bait": false,
		"detect_item": false,
		"item_name": "Alligator"
	},
	"Angelfish": {
		"script": "ExtResource( 1 )",
		"item_description": "Pterophyllum scalare",
		"catch_blurb": "Obtuse or acute? (... did i read that right?).",
		"item_is_hidden": false,
		"icon": "ExtResource( 2 )",
		"show_item": true,
		"show_scene": false,
		"uses_size": true,
		"action": "",
		"action_params": [],
		"release_action": "",
		"prop_code": "",
		"help_text": "",
		"arm_value": 0.2,
		"hold_offset": 0.0,
		"unselectable": false,
		"category": "fish",
		"alive": true,
		"tier": 0,
		"catch_difficulty": 1.1,
		"catch_speed": 120.0,
		"loot_table": "ocean",
		"loot_weight": 0.9,
		"average_size": 20.0,
		"sell_value": 14,
		"obtain_xp": 40,
		"generate_worth": true,
		"can_be_sold": true,
		"show_bait": false,
		"detect_item": false,
		"item_name": "Angelfish"
	},
	"Anomalocaris": {
		"script": "ExtResource( 1 )",
		"item_description": "Anomalocaris canadensis",
		"catch_blurb": "Doing it's best :)",
		"item_is_hidden": false,
		"icon": "ExtResource( 2 )",
		"show_item": true,
		"show_scene": false,
		"uses_size": true,
		"action": "",
		"action_params": [],
		"release_action": "",
		"prop_code": "",
		"help_text": "",
		"arm_value": 0.2,
		"hold_offset": 0.0,
		"unselectable": false,
		"unrenamable": false,
		"category": "fish",
		"alive": true,
		"tier": 0,
		"catch_difficulty": 4.0,
		"catch_speed": 120.0,
		"loot_table": "rain",
		"loot_weight": 1.0,
		"average_size": 45.0,
		"sell_value": 1,
		"sell_multiplier": 2.0,
		"obtain_xp": 100,
		"generate_worth": true,
		"can_be_sold": true,
		"rare": false,
		"stackable": false,
		"max_stacks": 99,
		"unobtainable": false,
		"show_bait": false,
		"detect_item": false,
		"item_name": "Anomalocaris"
	},
	"Atlantic Salmon": {
		"script": "ExtResource( 1 )",
		"item_description": "Salmo salar",
		"catch_blurb": "It's like non-atlantic salmon but atlantic",
		"item_is_hidden": false,
		"icon": "ExtResource( 2 )",
		"show_item": true,
		"show_scene": false,
		"uses_size": true,
		"action": "",
		"action_params": [],
		"release_action": "",
		"prop_code": "",
		"help_text": "",
		"arm_value": 0.2,
		"hold_offset": 0.0,
		"unselectable": false,
		"category": "fish",
		"alive": true,
		"tier": 0,
		"catch_difficulty": 1.5,
		"catch_speed": 120.0,
		"loot_table": "ocean",
		"loot_weight": 1.2,
		"average_size": 35.0,
		"sell_value": 9,
		"obtain_xp": 30,
		"generate_worth": true,
		"can_be_sold": true,
		"show_bait": false,
		"detect_item": false,
		"item_name": "Atlantic Salmon"
	},
	"Axolotl": {
		"script": "ExtResource( 1 )",
		"item_description": "Ambystoma mexicanum",
		"catch_blurb": "Can I ax-olotl you a question? (...I tried, ok?)",
		"item_is_hidden": false,
		"icon": "ExtResource( 2 )",
		"show_item": true,
		"show_scene": false,
		"uses_size": true,
		"action": "",
		"action_params": [],
		"release_action": "",
		"prop_code": "",
		"help_text": "",
		"arm_value": 0.2,
		"hold_offset": 0.0,
		"unselectable": false,
		"category": "fish",
		"alive": true,
		"tier": 2,
		"catch_difficulty": 4.0,
		"catch_speed": 120.0,
		"loot_table": "lake",
		"loot_weight": 0.14,
		"average_size": 30.0,
		"sell_value": 90,
		"obtain_xp": 125,
		"generate_worth": true,
		"can_be_sold": true,
		"show_bait": false,
		"detect_item": false,
		"item_name": "Axolotl"
	},
	"Blade Fragment": {
		"script": "ExtResource( 1 )",
		"item_description": "Shiny!",
		"catch_blurb": "Woah! Wonder if anyone wants this...",
		"item_is_hidden": false,
		"icon": "ExtResource( 2 )",
		"show_item": true,
		"show_scene": false,
		"uses_size": true,
		"action": "",
		"action_params": [],
		"release_action": "",
		"prop_code": "",
		"help_text": "",
		"arm_value": 0.2,
		"hold_offset": 0.0,
		"unselectable": false,
		"category": "fish",
		"alive": false,
		"tier": 0,
		"catch_difficulty": 1.0,
		"catch_speed": 120.0,
		"loot_table": "metal",
		"loot_weight": 0.18,
		"average_size": 8.0,
		"sell_value": 50,
		"obtain_xp": 30,
		"generate_worth": false,
		"can_be_sold": true,
		"show_bait": false,
		"detect_item": false,
		"item_name": "Blade Fragment"
	},
	"Bluefish": {
		"script": "ExtResource( 1 )",
		"item_description": "Pomatomus saltatrix",
		"catch_blurb": "One fish, two fish, red fish...",
		"item_is_hidden": false,
		"icon": "ExtResource( 2 )",
		"show_item": true,
		"show_scene": false,
		"uses_size": true,
		"action": "",
		"action_params": [],
		"release_action": "",
		"prop_code": "",
		"help_text": "",
		"arm_value": 0.2,
		"hold_offset": 0.0,
		"unselectable": false,
		"category": "fish",
		"alive": true,
		"tier": 0,
		"catch_difficulty": 1.5,
		"catch_speed": 120.0,
		"loot_table": "ocean",
		"loot_weight": 0.75,
		"average_size": 85.0,
		"sell_value": 14,
		"obtain_xp": 28,
		"generate_worth": true,
		"can_be_sold": true,
		"show_bait": false,
		"detect_item": false,
		"item_name": "Bluefish"
	},
	"Bluegill": {
		"script": "ExtResource( 1 )",
		"item_description": "Lepomis macrochirus",
		"catch_blurb": "Bluegill? What a thrill!",
		"item_is_hidden": false,
		"icon": "ExtResource( 2 )",
		"show_item": true,
		"show_scene": false,
		"uses_size": true,
		"action": "",
		"action_params": [],
		"release_action": "",
		"prop_code": "",
		"help_text": "",
		"arm_value": 0.2,
		"hold_offset": 0.0,
		"unselectable": false,
		"category": "fish",
		"alive": true,
		"tier": 0,
		"catch_difficulty": 1.5,
		"catch_speed": 120.0,
		"loot_table": "lake",
		"loot_weight": 1.15,
		"average_size": 15.0,
		"sell_value": 9,
		"obtain_xp": 35,
		"generate_worth": true,
		"can_be_sold": true,
		"show_bait": false,
		"detect_item": false,
		"item_name": "Bluegill"
	},
	"Bone": {
		"script": "ExtResource( 1 )",
		"item_description": "What a story!",
		"catch_blurb": "Yuck! Who put this in here...",
		"item_is_hidden": false,
		"icon": "ExtResource( 2 )",
		"show_item": true,
		"show_scene": false,
		"uses_size": true,
		"action": "",
		"action_params": [],
		"release_action": "",
		"prop_code": "",
		"help_text": "",
		"arm_value": 0.2,
		"hold_offset": 0.0,
		"unselectable": false,
		"category": "fish",
		"alive": false,
		"tier": 0,
		"catch_difficulty": 1.0,
		"catch_speed": 120.0,
		"loot_table": "water_trash",
		"loot_weight": 0.25,
		"average_size": 12.0,
		"sell_value": 15,
		"obtain_xp": 30,
		"generate_worth": false,
		"can_be_sold": true,
		"show_bait": false,
		"detect_item": false,
		"item_name": "Bone"
	},
	"Bowfin": {
		"script": "ExtResource( 1 )",
		"item_description": "Amia calva",
		"catch_blurb": "Bowfin deez n-",
		"item_is_hidden": false,
		"icon": "ExtResource( 2 )",
		"show_item": true,
		"show_scene": false,
		"uses_size": true,
		"action": "",
		"action_params": [],
		"release_action": "",
		"prop_code": "",
		"help_text": "",
		"arm_value": 0.2,
		"hold_offset": 0.0,
		"unselectable": false,
		"category": "fish",
		"alive": true,
		"tier": 1,
		"catch_difficulty": 2.7,
		"catch_speed": 120.0,
		"loot_table": "lake",
		"loot_weight": 0.5,
		"average_size": 75.0,
		"sell_value": 35,
		"obtain_xp": 50,
		"generate_worth": true,
		"can_be_sold": true,
		"show_bait": false,
		"detect_item": false,
		"item_name": "Bowfin"
	},
	"Branch": {
		"script": "ExtResource( 1 )",
		"item_description": "Stick!",
		"catch_blurb": "Agh! Caught a snag!",
		"item_is_hidden": false,
		"icon": "ExtResource( 2 )",
		"show_item": true,
		"show_scene": false,
		"uses_size": true,
		"action": "",
		"action_params": [],
		"release_action": "",
		"prop_code": "",
		"help_text": "",
		"arm_value": 0.2,
		"hold_offset": 0.0,
		"unselectable": false,
		"category": "fish",
		"alive": false,
		"tier": 0,
		"catch_difficulty": 1.0,
		"catch_speed": 120.0,
		"loot_table": "water_trash",
		"loot_weight": 1.0,
		"average_size": 15.0,
		"sell_value": 5,
		"obtain_xp": 30,
		"generate_worth": false,
		"can_be_sold": true,
		"show_bait": false,
		"detect_item": false,
		"item_name": "Branch"
	},
	"Bull Shark": {
		"script": "ExtResource( 1 )",
		"item_description": "Carcharhinus leucas",
		"catch_blurb": "Bullshark? Bull S-",
		"item_is_hidden": false,
		"icon": "ExtResource( 2 )",
		"show_item": true,
		"show_scene": false,
		"uses_size": true,
		"action": "",
		"action_params": [],
		"release_action": "",
		"prop_code": "",
		"help_text": "",
		"arm_value": 0.2,
		"hold_offset": 0.0,
		"unselectable": false,
		"category": "fish",
		"alive": true,
		"tier": 2,
		"catch_difficulty": 6.5,
		"catch_speed": 120.0,
		"loot_table": "lake",
		"loot_weight": 0.08,
		"average_size": 240.0,
		"sell_value": 125,
		"obtain_xp": 150,
		"generate_worth": true,
		"can_be_sold": true,
		"show_bait": false,
		"detect_item": false,
		"item_name": "Bull Shark"
	},
	"Button": {
		"script": "ExtResource( 1 )",
		"item_description": "Filthy...",
		"catch_blurb": "Not the most interesting find, for sure...",
		"item_is_hidden": false,
		"icon": "ExtResource( 2 )",
		"show_item": true,
		"show_scene": false,
		"uses_size": true,
		"action": "",
		"action_params": [],
		"release_action": "",
		"prop_code": "",
		"help_text": "",
		"arm_value": 0.2,
		"hold_offset": 0.0,
		"unselectable": false,
		"category": "fish",
		"alive": false,
		"tier": 0,
		"catch_difficulty": 1.0,
		"catch_speed": 120.0,
		"loot_table": "metal",
		"loot_weight": 1.0,
		"average_size": 8.0,
		"sell_value": 3,
		"obtain_xp": 30,
		"generate_worth": false,
		"can_be_sold": true,
		"show_bait": false,
		"detect_item": false,
		"item_name": "Button"
	},
	"CREATURE": {
		"script": "ExtResource( 1 )",
		"item_description": "rraim eor",
		"catch_blurb": "NiceCatch!NiceCatch!NiceCatch!NiceCatch!NiceCatch!NiceCatch!NiceCatch!NiceCatch!NiceCatch!NiceCatch!",
		"item_is_hidden": false,
		"icon": "ExtResource( 2 )",
		"show_item": true,
		"show_scene": false,
		"uses_size": true,
		"action": "",
		"action_params": [],
		"release_action": "",
		"prop_code": "",
		"help_text": "",
		"arm_value": 0.2,
		"hold_offset": 0.0,
		"unselectable": false,
		"unrenamable": false,
		"category": "fish",
		"alive": true,
		"tier": 1,
		"catch_difficulty": 5.8,
		"catch_speed": 120.0,
		"loot_table": "void",
		"loot_weight": 1.0,
		"average_size": 90.0,
		"sell_value": 1,
		"sell_multiplier": 3.5,
		"obtain_xp": 100,
		"generate_worth": true,
		"can_be_sold": true,
		"rare": false,
		"stackable": false,
		"max_stacks": 99,
		"unobtainable": false,
		"show_bait": false,
		"detect_item": false,
		"item_name": "CREATURE"
	},
	"Carp": {
		"script": "ExtResource( 1 )",
		"item_description": "Cyprinus carpio",
		"catch_blurb": "Carp? What a lark!",
		"item_is_hidden": false,
		"icon": "ExtResource( 2 )",
		"show_item": true,
		"show_scene": false,
		"uses_size": true,
		"action": "",
		"action_params": [],
		"release_action": "",
		"prop_code": "",
		"help_text": "",
		"arm_value": 0.2,
		"hold_offset": 0.0,
		"unselectable": false,
		"category": "fish",
		"alive": true,
		"tier": 0,
		"catch_difficulty": 1.5,
		"catch_speed": 120.0,
		"loot_table": "lake",
		"loot_weight": 1.25,
		"average_size": 55.0,
		"sell_value": 8,
		"obtain_xp": 35,
		"generate_worth": true,
		"can_be_sold": true,
		"show_bait": false,
		"detect_item": false,
		"item_name": "Carp"
	},
	"Casing": {
		"script": "ExtResource( 1 )",
		"item_description": "What a story...",
		"catch_blurb": "Woah! Wonder what happened here...",
		"item_is_hidden": false,
		"icon": "ExtResource( 2 )",
		"show_item": true,
		"show_scene": false,
		"uses_size": true,
		"action": "",
		"action_params": [],
		"release_action": "",
		"prop_code": "",
		"help_text": "",
		"arm_value": 0.2,
		"hold_offset": 0.0,
		"unselectable": false,
		"category": "fish",
		"alive": false,
		"tier": 0,
		"catch_difficulty": 1.0,
		"catch_speed": 120.0,
		"loot_table": "metal",
		"loot_weight": 0.2,
		"average_size": 8.0,
		"sell_value": 35,
		"sell_multiplier": 1.0,
		"obtain_xp": 30,
		"generate_worth": false,
		"can_be_sold": true,
		"rare": false,
		"show_bait": false,
		"detect_item": false,
		"item_name": "Casing"
	},
	"Catfish": {
		"script": "ExtResource( 1 )",
		"item_description": "Ictalurus punctatus",
		"catch_blurb": "He's just like you! But yknow... more... fishy?",
		"item_is_hidden": false,
		"icon": "ExtResource( 2 )",
		"show_item": true,
		"show_scene": false,
		"uses_size": true,
		"action": "",
		"action_params": [],
		"release_action": "",
		"prop_code": "",
		"help_text": "",
		"arm_value": 0.2,
		"hold_offset": 0.0,
		"unselectable": false,
		"category": "fish",
		"alive": true,
		"tier": 0,
		"catch_difficulty": 2.0,
		"catch_speed": 120.0,
		"loot_table": "lake",
		"loot_weight": 0.35,
		"average_size": 65.0,
		"sell_value": 30,
		"obtain_xp": 50,
		"generate_worth": true,
		"can_be_sold": true,
		"show_bait": false,
		"detect_item": false,
		"item_name": "Catfish"
	},
	"Clownfish": {
		"script": "ExtResource( 1 )",
		"item_description": "Amphiprion ocellaris",
		"catch_blurb": "Well this isnt so scary...",
		"item_is_hidden": false,
		"icon": "ExtResource( 2 )",
		"show_item": true,
		"show_scene": false,
		"uses_size": true,
		"action": "",
		"action_params": [],
		"release_action": "",
		"prop_code": "",
		"help_text": "",
		"arm_value": 0.2,
		"hold_offset": 0.0,
		"unselectable": false,
		"category": "fish",
		"alive": true,
		"tier": 0,
		"catch_difficulty": 1.2,
		"catch_speed": 120.0,
		"loot_table": "ocean",
		"loot_weight": 1.0,
		"average_size": 15.0,
		"sell_value": 9,
		"obtain_xp": 35,
		"generate_worth": true,
		"can_be_sold": true,
		"show_bait": false,
		"detect_item": false,
		"item_name": "Clownfish"
	},
	"Coelacanth": {
		"script": "ExtResource( 1 )",
		"item_description": "Latimeria chalumnae",
		"catch_blurb": "Did you see it? I can't!",
		"item_is_hidden": false,
		"icon": "ExtResource( 2 )",
		"show_item": true,
		"show_scene": false,
		"uses_size": true,
		"action": "",
		"action_params": [],
		"release_action": "",
		"prop_code": "",
		"help_text": "",
		"arm_value": 0.2,
		"hold_offset": 0.0,
		"unselectable": false,
		"category": "fish",
		"alive": true,
		"tier": 2,
		"catch_difficulty": 5.5,
		"catch_speed": 120.0,
		"loot_table": "ocean",
		"loot_weight": 0.1,
		"average_size": 180.0,
		"sell_value": 30,
		"sell_multiplier": 1.0,
		"obtain_xp": 60,
		"generate_worth": true,
		"can_be_sold": true,
		"rare": false,
		"show_bait": false,
		"detect_item": false,
		"item_name": "Coelacanth"
	},
	"Crab": {
		"script": "ExtResource( 1 )",
		"item_description": "Uca minax",
		"catch_blurb": "Arg!",
		"item_is_hidden": false,
		"icon": "ExtResource( 2 )",
		"show_item": true,
		"show_scene": false,
		"uses_size": true,
		"action": "",
		"action_params": [],
		"release_action": "",
		"prop_code": "",
		"help_text": "",
		"arm_value": 0.2,
		"hold_offset": 0.0,
		"unselectable": false,
		"category": "fish",
		"alive": true,
		"tier": 1,
		"catch_difficulty": 2.5,
		"catch_speed": 120.0,
		"loot_table": "lake",
		"loot_weight": 0.65,
		"average_size": 8.0,
		"sell_value": 25,
		"obtain_xp": 45,
		"generate_worth": true,
		"can_be_sold": true,
		"show_bait": false,
		"detect_item": false,
		"item_name": "Crab"
	},
	"Crappie": {
		"script": "ExtResource( 1 )",
		"item_description": "Pomoxis annularis",
		"catch_blurb": "Holy Crappie!",
		"item_is_hidden": false,
		"icon": "ExtResource( 2 )",
		"show_item": true,
		"show_scene": false,
		"uses_size": true,
		"action": "",
		"action_params": [],
		"release_action": "",
		"prop_code": "",
		"help_text": "",
		"arm_value": 0.2,
		"hold_offset": 0.0,
		"unselectable": false,
		"category": "fish",
		"alive": true,
		"tier": 1,
		"catch_difficulty": 2.5,
		"catch_speed": 120.0,
		"loot_table": "lake",
		"loot_weight": 0.55,
		"average_size": 25.0,
		"sell_value": 20,
		"obtain_xp": 50,
		"generate_worth": true,
		"can_be_sold": true,
		"show_bait": false,
		"detect_item": false,
		"item_name": "Crappie"
	},
	"Crayfish": {
		"script": "ExtResource( 1 )",
		"item_description": "Procambarus clarkii",
		"catch_blurb": "Blah blah blah.",
		"item_is_hidden": false,
		"icon": "ExtResource( 2 )",
		"show_item": true,
		"show_scene": false,
		"uses_size": true,
		"action": "",
		"action_params": [],
		"release_action": "",
		"prop_code": "",
		"help_text": "",
		"arm_value": 0.2,
		"hold_offset": 0.0,
		"unselectable": false,
		"category": "fish",
		"alive": true,
		"tier": 0,
		"catch_difficulty": 1.6,
		"catch_speed": 120.0,
		"loot_table": "lake",
		"loot_weight": 0.8,
		"average_size": 10.0,
		"sell_value": 12,
		"obtain_xp": 40,
		"generate_worth": true,
		"can_be_sold": true,
		"show_bait": false,
		"detect_item": false,
		"item_name": "Crayfish"
	},
	"Diamond": {
		"script": "ExtResource( 1 )",
		"item_description": "Shiny!",
		"catch_blurb": "Dug right out of the rough!",
		"item_is_hidden": false,
		"icon": "ExtResource( 2 )",
		"show_item": true,
		"show_scene": false,
		"uses_size": true,
		"action": "",
		"action_params": [],
		"release_action": "",
		"prop_code": "",
		"help_text": "",
		"arm_value": 0.2,
		"hold_offset": 0.0,
		"unselectable": false,
		"category": "fish",
		"alive": false,
		"tier": 0,
		"catch_difficulty": 1.0,
		"catch_speed": 120.0,
		"loot_table": "water_trash",
		"loot_weight": 0.18,
		"average_size": 40.0,
		"sell_value": 100,
		"sell_multiplier": 2.0,
		"obtain_xp": 50,
		"generate_worth": false,
		"can_be_sold": true,
		"rare": true,
		"show_bait": false,
		"detect_item": false,
		"item_name": "Diamond"
	},
	"Dogfish": {
		"script": "ExtResource( 1 )",
		"item_description": "Squalus acanthias",
		"catch_blurb": "He's just like you! But yknow... more... fishy?",
		"item_is_hidden": false,
		"icon": "ExtResource( 2 )",
		"show_item": true,
		"show_scene": false,
		"uses_size": true,
		"action": "",
		"action_params": [],
		"release_action": "",
		"prop_code": "",
		"help_text": "",
		"arm_value": 0.2,
		"hold_offset": 0.0,
		"unselectable": false,
		"category": "fish",
		"alive": true,
		"tier": 0,
		"catch_difficulty": 3.0,
		"catch_speed": 120.0,
		"loot_table": "ocean",
		"loot_weight": 0.3,
		"average_size": 80.0,
		"sell_value": 25,
		"obtain_xp": 45,
		"generate_worth": true,
		"can_be_sold": true,
		"show_bait": false,
		"detect_item": false,
		"item_name": "Dogfish"
	},
	"Drink Rings": {
		"script": "ExtResource( 1 )",
		"item_description": "Don't Litter!",
		"catch_blurb": "Yuck! Who put this in here...",
		"item_is_hidden": false,
		"icon": "ExtResource( 2 )",
		"show_item": true,
		"show_scene": false,
		"uses_size": true,
		"action": "",
		"action_params": [],
		"release_action": "",
		"prop_code": "",
		"help_text": "",
		"arm_value": 0.2,
		"hold_offset": 0.0,
		"unselectable": false,
		"category": "fish",
		"alive": false,
		"tier": 0,
		"catch_difficulty": 1.0,
		"catch_speed": 120.0,
		"loot_table": "water_trash",
		"loot_weight": 1.0,
		"average_size": 14.0,
		"sell_value": 5,
		"obtain_xp": 30,
		"generate_worth": false,
		"can_be_sold": true,
		"show_bait": false,
		"detect_item": false,
		"item_name": "Drink Rings"
	},
	"Drum": {
		"script": "ExtResource( 1 )",
		"item_description": "Aplodinotus grunniens",
		"catch_blurb": "Also known as the Gooble Gobble. Real fact.",
		"item_is_hidden": false,
		"icon": "ExtResource( 2 )",
		"show_item": true,
		"show_scene": false,
		"uses_size": true,
		"action": "",
		"action_params": [],
		"release_action": "",
		"prop_code": "",
		"help_text": "",
		"arm_value": 0.2,
		"hold_offset": 0.0,
		"unselectable": false,
		"category": "fish",
		"alive": true,
		"tier": 0,
		"catch_difficulty": 1.5,
		"catch_speed": 120.0,
		"loot_table": "lake",
		"loot_weight": 0.8,
		"average_size": 25.0,
		"sell_value": 10,
		"obtain_xp": 40,
		"generate_worth": true,
		"can_be_sold": true,
		"show_bait": false,
		"detect_item": false,
		"item_name": "Drum"
	},
	"Eel": {
		"script": "ExtResource( 1 )",
		"item_description": "Anguilla anguilla",
		"catch_blurb": "Eel? EEL!",
		"item_is_hidden": false,
		"icon": "ExtResource( 2 )",
		"show_item": true,
		"show_scene": false,
		"uses_size": true,
		"action": "",
		"action_params": [],
		"release_action": "",
		"prop_code": "",
		"help_text": "",
		"arm_value": 0.2,
		"hold_offset": 0.0,
		"unselectable": false,
		"category": "fish",
		"alive": true,
		"tier": 0,
		"catch_difficulty": 3.5,
		"catch_speed": 120.0,
		"loot_table": "ocean",
		"loot_weight": 0.35,
		"average_size": 55.0,
		"sell_value": 35,
		"obtain_xp": 80,
		"generate_worth": true,
		"can_be_sold": true,
		"show_bait": false,
		"detect_item": false,
		"item_name": "Eel"
	},
	"Flounder": {
		"script": "ExtResource( 1 )",
		"item_description": "Paralichthys dentatus",
		"catch_blurb": "Flounder? I hardly know 'er!",
		"item_is_hidden": false,
		"icon": "ExtResource( 2 )",
		"show_item": true,
		"show_scene": false,
		"uses_size": true,
		"action": "",
		"action_params": [],
		"release_action": "",
		"prop_code": "",
		"help_text": "",
		"arm_value": 0.2,
		"hold_offset": 0.0,
		"unselectable": false,
		"category": "fish",
		"alive": true,
		"tier": 0,
		"catch_difficulty": 1.5,
		"catch_speed": 120.0,
		"loot_table": "ocean",
		"loot_weight": 1.15,
		"average_size": 45.0,
		"sell_value": 10,
		"obtain_xp": 35,
		"generate_worth": true,
		"can_be_sold": true,
		"show_bait": false,
		"detect_item": false,
		"item_name": "Flounder"
	},
	"Frog": {
		"script": "ExtResource( 1 )",
		"item_description": "Rana temporaria",
		"catch_blurb": "Cozy Staple.",
		"item_is_hidden": false,
		"icon": "ExtResource( 2 )",
		"show_item": true,
		"show_scene": false,
		"uses_size": true,
		"action": "",
		"action_params": [],
		"release_action": "",
		"prop_code": "",
		"help_text": "",
		"arm_value": 0.2,
		"hold_offset": 0.0,
		"unselectable": false,
		"category": "fish",
		"alive": true,
		"tier": 0,
		"catch_difficulty": 1.5,
		"catch_speed": 120.0,
		"loot_table": "lake",
		"loot_weight": 0.4,
		"average_size": 6.0,
		"sell_value": 25,
		"obtain_xp": 50,
		"generate_worth": true,
		"can_be_sold": true,
		"show_bait": false,
		"detect_item": false,
		"item_name": "Frog"
	},
	"Gar": {
		"script": "ExtResource( 1 )",
		"item_description": "Atractosteus spatula",
		"catch_blurb": "Step-Brother of the Alligator!",
		"item_is_hidden": false,
		"icon": "ExtResource( 2 )",
		"show_item": true,
		"show_scene": false,
		"uses_size": true,
		"action": "",
		"action_params": [],
		"release_action": "",
		"prop_code": "",
		"help_text": "",
		"arm_value": 0.2,
		"hold_offset": 0.0,
		"unselectable": false,
		"category": "fish",
		"alive": true,
		"tier": 2,
		"catch_difficulty": 5.0,
		"catch_speed": 120.0,
		"loot_table": "lake",
		"loot_weight": 0.18,
		"average_size": 175.0,
		"sell_value": 80,
		"obtain_xp": 100,
		"generate_worth": true,
		"can_be_sold": true,
		"show_bait": false,
		"detect_item": false,
		"item_name": "Gar"
	},
	"Golden Bass": {
		"script": "ExtResource( 1 )",
		"item_description": "Micropterus aurum",
		"catch_blurb": "Woah! What a catch!",
		"item_is_hidden": false,
		"icon": "ExtResource( 2 )",
		"show_item": true,
		"show_scene": false,
		"uses_size": true,
		"action": "",
		"action_params": [],
		"release_action": "",
		"prop_code": "",
		"help_text": "",
		"arm_value": 0.2,
		"hold_offset": 0.0,
		"unselectable": false,
		"category": "fish",
		"alive": true,
		"tier": 2,
		"catch_difficulty": 6.0,
		"catch_speed": 120.0,
		"loot_table": "lake",
		"loot_weight": 0.03,
		"average_size": 45.0,
		"sell_value": 300,
		"sell_multiplier": 1.0,
		"obtain_xp": 200,
		"generate_worth": true,
		"can_be_sold": true,
		"rare": true,
		"show_bait": false,
		"detect_item": false,
		"item_name": "Golden Bass"
	},
	"Golden Manta Ray": {
		"script": "ExtResource( 1 )",
		"item_description": "Mobula aurum",
		"catch_blurb": "Woah! What a catch!",
		"item_is_hidden": false,
		"icon": "ExtResource( 2 )",
		"show_item": true,
		"show_scene": false,
		"uses_size": true,
		"action": "",
		"action_params": [],
		"release_action": "",
		"prop_code": "",
		"help_text": "",
		"arm_value": 0.2,
		"hold_offset": 0.0,
		"unselectable": false,
		"category": "fish",
		"alive": true,
		"tier": 2,
		"catch_difficulty": 5.5,
		"catch_speed": 120.0,
		"loot_table": "ocean",
		"loot_weight": 0.03,
		"average_size": 600.0,
		"sell_value": 30,
		"sell_multiplier": 1.0,
		"obtain_xp": 60,
		"generate_worth": true,
		"can_be_sold": true,
		"rare": true,
		"show_bait": false,
		"detect_item": false,
		"item_name": "Golden Manta Ray"
	},
	"Goldfish": {
		"script": "ExtResource( 1 )",
		"item_description": "Carassius auratus",
		"catch_blurb": "We're rich!",
		"item_is_hidden": false,
		"icon": "ExtResource( 2 )",
		"show_item": true,
		"show_scene": false,
		"uses_size": true,
		"action": "",
		"action_params": [],
		"release_action": "",
		"prop_code": "",
		"help_text": "",
		"arm_value": 0.2,
		"hold_offset": 0.0,
		"unselectable": false,
		"category": "fish",
		"alive": true,
		"tier": 0,
		"catch_difficulty": 1.4,
		"catch_speed": 120.0,
		"loot_table": "lake",
		"loot_weight": 0.9,
		"average_size": 15.0,
		"sell_value": 14,
		"obtain_xp": 35,
		"generate_worth": true,
		"can_be_sold": true,
		"show_bait": false,
		"detect_item": false,
		"item_name": "Goldfish"
	},
	"Great White Shark": {
		"script": "ExtResource( 1 )",
		"item_description": "Carcharodon carcharias",
		"catch_blurb": "Do I smell blood...?",
		"item_is_hidden": false,
		"icon": "ExtResource( 2 )",
		"show_item": true,
		"show_scene": false,
		"uses_size": true,
		"action": "",
		"action_params": [],
		"release_action": "",
		"prop_code": "",
		"help_text": "",
		"arm_value": 0.2,
		"hold_offset": 0.0,
		"unselectable": false,
		"category": "fish",
		"alive": true,
		"tier": 2,
		"catch_difficulty": 6.0,
		"catch_speed": 120.0,
		"loot_table": "ocean",
		"loot_weight": 0.12,
		"average_size": 180.0,
		"sell_value": 30,
		"obtain_xp": 60,
		"generate_worth": true,
		"can_be_sold": true,
		"show_bait": false,
		"detect_item": false,
		"item_name": "Great White Shark"
	},
	"Grouper": {
		"script": "ExtResource( 1 )",
		"item_description": "Mycteroperca bonaci",
		"catch_blurb": "Grouper? I hardly know 'er!",
		"item_is_hidden": false,
		"icon": "ExtResource( 2 )",
		"show_item": true,
		"show_scene": false,
		"uses_size": true,
		"action": "",
		"action_params": [],
		"release_action": "",
		"prop_code": "",
		"help_text": "",
		"arm_value": 0.2,
		"hold_offset": 0.0,
		"unselectable": false,
		"category": "fish",
		"alive": true,
		"tier": 0,
		"catch_difficulty": 1.5,
		"catch_speed": 120.0,
		"loot_table": "ocean",
		"loot_weight": 0.9,
		"average_size": 110.0,
		"sell_value": 12,
		"obtain_xp": 40,
		"can_be_sold": true,
		"show_bait": false,
		"item_name": "Grouper"
	},
	"Guppy": {
		"script": "ExtResource( 1 )",
		"item_description": "Poecilia reticulata",
		"catch_blurb": "Guess you're a guppy puppy!",
		"item_is_hidden": false,
		"icon": "ExtResource( 2 )",
		"show_item": true,
		"show_scene": false,
		"uses_size": true,
		"action": "",
		"action_params": [],
		"release_action": "",
		"prop_code": "",
		"help_text": "",
		"arm_value": 0.2,
		"hold_offset": 0.0,
		"unselectable": false,
		"category": "fish",
		"alive": true,
		"tier": 0,
		"catch_difficulty": 1.0,
		"catch_speed": 120.0,
		"loot_table": "lake",
		"loot_weight": 0.65,
		"average_size": 4.0,
		"sell_value": 16,
		"obtain_xp": 40,
		"generate_worth": true,
		"can_be_sold": true,
		"show_bait": false,
		"detect_item": false,
		"item_name": "Guppy"
	},
	"Hammerhead Shark": {
		"script": "ExtResource( 1 )",
		"item_description": "Sphyrna mokarran",
		"catch_blurb": "Guess you hit the nail on the head!",
		"item_is_hidden": false,
		"icon": "ExtResource( 2 )",
		"show_item": true,
		"show_scene": false,
		"uses_size": true,
		"action": "",
		"action_params": [],
		"release_action": "",
		"prop_code": "",
		"help_text": "",
		"arm_value": 0.2,
		"hold_offset": 0.0,
		"unselectable": false,
		"category": "fish",
		"alive": true,
		"tier": 1,
		"catch_difficulty": 4.5,
		"catch_speed": 120.0,
		"loot_table": "ocean",
		"loot_weight": 0.35,
		"average_size": 300.0,
		"sell_value": 30,
		"obtain_xp": 60,
		"generate_worth": true,
		"can_be_sold": true,
		"show_bait": false,
		"detect_item": false,
		"item_name": "Hammerhead Shark"
	},
	"Hat Fragment": {
		"script": "ExtResource( 1 )",
		"item_description": "Shiny!",
		"catch_blurb": "Woah! Wonder if anyone wants this...",
		"item_is_hidden": false,
		"icon": "ExtResource( 2 )",
		"show_item": true,
		"show_scene": false,
		"uses_size": true,
		"action": "",
		"action_params": [],
		"release_action": "",
		"prop_code": "",
		"help_text": "",
		"arm_value": 0.2,
		"hold_offset": 0.0,
		"unselectable": false,
		"category": "fish",
		"alive": false,
		"tier": 0,
		"catch_difficulty": 1.0,
		"catch_speed": 120.0,
		"loot_table": "metal",
		"loot_weight": 0.18,
		"average_size": 8.0,
		"sell_value": 50,
		"obtain_xp": 30,
		"generate_worth": false,
		"can_be_sold": true,
		"show_bait": false,
		"detect_item": false,
		"item_name": "Hat Fragment"
	},
	"Helicoprion": {
		"script": "ExtResource( 1 )",
		"item_description": "Helicoprion bessonowi",
		"catch_blurb": "Nature's pizza cutter!",
		"item_is_hidden": false,
		"icon": "ExtResource( 2 )",
		"show_item": true,
		"show_scene": false,
		"uses_size": true,
		"action": "",
		"action_params": [],
		"release_action": "",
		"prop_code": "",
		"help_text": "",
		"arm_value": 0.2,
		"hold_offset": 0.0,
		"unselectable": false,
		"category": "fish",
		"alive": true,
		"tier": 1,
		"catch_difficulty": 5.8,
		"catch_speed": 120.0,
		"loot_table": "rain",
		"loot_weight": 0.3,
		"average_size": 600.0,
		"sell_value": 1,
		"sell_multiplier": 3.5,
		"obtain_xp": 100,
		"generate_worth": true,
		"can_be_sold": true,
		"rare": false,
		"show_bait": false,
		"detect_item": false,
		"item_name": "Helicoprion"
	},
	"Herring": {
		"script": "ExtResource( 1 )",
		"item_description": "Clupea harengus",
		"catch_blurb": "Huh... this isnt red...",
		"item_is_hidden": false,
		"icon": "ExtResource( 2 )",
		"show_item": true,
		"show_scene": false,
		"uses_size": true,
		"action": "",
		"action_params": [],
		"release_action": "",
		"help_text": "",
		"arm_value": 0.2,
		"hold_offset": 0.0,
		"unselectable": false,
		"category": "fish",
		"alive": true,
		"tier": 0,
		"catch_difficulty": 1.5,
		"catch_speed": 120.0,
		"loot_table": "ocean",
		"loot_weight": 1.2,
		"average_size": 30.0,
		"sell_value": 9,
		"obtain_xp": 30,
		"can_be_sold": true,
		"show_bait": false,
		"item_name": "Herring"
	},
	"Horseshoe Crab": {
		"script": "ExtResource( 1 )",
		"item_description": "Tachypleus tridentatus",
		"catch_blurb": "Guess it's my lucky day!",
		"item_is_hidden": false,
		"icon": "ExtResource( 2 )",
		"show_item": true,
		"show_scene": false,
		"uses_size": true,
		"action": "",
		"action_params": [],
		"release_action": "",
		"prop_code": "",
		"help_text": "",
		"arm_value": 0.2,
		"hold_offset": 0.0,
		"unselectable": false,
		"category": "fish",
		"alive": true,
		"tier": 0,
		"catch_difficulty": 4.0,
		"catch_speed": 120.0,
		"loot_table": "rain",
		"loot_weight": 1.0,
		"average_size": 45.0,
		"sell_value": 1,
		"sell_multiplier": 2.0,
		"obtain_xp": 100,
		"generate_worth": true,
		"can_be_sold": true,
		"show_bait": false,
		"detect_item": false,
		"item_name": "Horseshoe Crab"
	},
	"King Salmon": {
		"script": "ExtResource( 1 )",
		"item_description": "Oncorhynchus tshawytscha",
		"catch_blurb": "Royalty!",
		"item_is_hidden": false,
		"icon": "ExtResource( 2 )",
		"show_item": true,
		"show_scene": false,
		"uses_size": true,
		"action": "",
		"action_params": [],
		"release_action": "",
		"prop_code": "",
		"help_text": "",
		"arm_value": 0.2,
		"hold_offset": 0.0,
		"unselectable": false,
		"category": "fish",
		"alive": true,
		"tier": 2,
		"catch_difficulty": 3.5,
		"catch_speed": 120.0,
		"loot_table": "lake",
		"loot_weight": 0.32,
		"average_size": 120.0,
		"sell_value": 75,
		"obtain_xp": 80,
		"generate_worth": true,
		"can_be_sold": true,
		"show_bait": false,
		"detect_item": false,
		"item_name": "King Salmon"
	},
	"Koi": {
		"script": "ExtResource( 1 )",
		"item_description": "Cyprinus rubrofuscus",
		"catch_blurb": "This koi is the boy for me!",
		"item_is_hidden": false,
		"icon": "ExtResource( 2 )",
		"show_item": true,
		"show_scene": false,
		"uses_size": true,
		"action": "",
		"action_params": [],
		"release_action": "",
		"prop_code": "",
		"help_text": "",
		"arm_value": 0.2,
		"hold_offset": 0.0,
		"unselectable": false,
		"category": "fish",
		"alive": true,
		"tier": 0,
		"catch_difficulty": 1.6,
		"catch_speed": 120.0,
		"loot_table": "lake",
		"loot_weight": 0.25,
		"average_size": 30.0,
		"sell_value": 25,
		"obtain_xp": 55,
		"generate_worth": true,
		"can_be_sold": true,
		"show_bait": false,
		"detect_item": false,
		"item_name": "Koi"
	},
	"Krill": {
		"script": "ExtResource( 1 )",
		"item_description": "Euphausia superba",
		"catch_blurb": "Shrimply impressive! (this isnt a shrimp btw)",
		"item_is_hidden": false,
		"icon": "ExtResource( 2 )",
		"show_item": true,
		"show_scene": false,
		"uses_size": true,
		"action": "",
		"action_params": [],
		"release_action": "",
		"prop_code": "",
		"help_text": "",
		"arm_value": 0.2,
		"hold_offset": 0.0,
		"unselectable": false,
		"category": "fish",
		"alive": true,
		"tier": 0,
		"catch_difficulty": 1.0,
		"catch_speed": 120.0,
		"loot_table": "ocean",
		"loot_weight": 0.8,
		"average_size": 5.0,
		"sell_value": 5,
		"obtain_xp": 25,
		"can_be_sold": true,
		"show_bait": false,
		"item_name": "Krill"
	},
	"Largemouth Bass": {
		"script": "ExtResource( 1 )",
		"item_description": "Micropterus salmoides",
		"catch_blurb": "Seems out of tune to me.",
		"item_is_hidden": false,
		"icon": "ExtResource( 2 )",
		"show_item": true,
		"show_scene": false,
		"uses_size": true,
		"action": "",
		"action_params": [],
		"release_action": "",
		"prop_code": "",
		"help_text": "",
		"arm_value": 0.2,
		"hold_offset": 0.0,
		"unselectable": false,
		"category": "fish",
		"alive": true,
		"tier": 0,
		"catch_difficulty": 1.5,
		"catch_speed": 120.0,
		"loot_table": "lake",
		"loot_weight": 1.25,
		"average_size": 45.0,
		"sell_value": 8,
		"obtain_xp": 35,
		"generate_worth": true,
		"can_be_sold": true,
		"show_bait": false,
		"detect_item": false,
		"item_name": "Largemouth Bass"
	},
	"Leech": {
		"script": "ExtResource( 1 )",
		"item_description": "Hirudo medicinalis",
		"catch_blurb": "Bringing back oldschool medicine!",
		"item_is_hidden": false,
		"icon": "ExtResource( 2 )",
		"show_item": true,
		"show_scene": false,
		"uses_size": true,
		"action": "",
		"action_params": [],
		"release_action": "",
		"prop_code": "",
		"help_text": "",
		"arm_value": 0.2,
		"hold_offset": 0.0,
		"unselectable": false,
		"category": "fish",
		"alive": true,
		"tier": 1,
		"catch_difficulty": 2.2,
		"catch_speed": 120.0,
		"loot_table": "lake",
		"loot_weight": 0.4,
		"average_size": 5.0,
		"sell_value": 30,
		"obtain_xp": 50,
		"generate_worth": true,
		"can_be_sold": true,
		"show_bait": false,
		"detect_item": false,
		"item_name": "Leech"
	},
	"Leedsichthys": {
		"script": "ExtResource( 1 )",
		"item_description": "Leedsichthys problematicus",
		"catch_blurb": "A giant!",
		"item_is_hidden": false,
		"icon": "ExtResource( 2 )",
		"show_item": true,
		"show_scene": false,
		"uses_size": true,
		"action": "",
		"action_params": [],
		"release_action": "",
		"prop_code": "",
		"help_text": "",
		"arm_value": 0.2,
		"hold_offset": 0.0,
		"unselectable": false,
		"category": "fish",
		"alive": true,
		"tier": 2,
		"catch_difficulty": 7.5,
		"catch_speed": 120.0,
		"loot_table": "rain",
		"loot_weight": 0.12,
		"average_size": 2700.0,
		"sell_value": 1,
		"sell_multiplier": 8.0,
		"obtain_xp": 300,
		"generate_worth": true,
		"can_be_sold": true,
		"rare": true,
		"show_bait": false,
		"detect_item": false,
		"item_name": "Leedsichthys"
	},
	"Lionfish": {
		"script": "ExtResource( 1 )",
		"item_description": "Pterois volitans",
		"catch_blurb": "Well I ain't callin' you a truther!",
		"item_is_hidden": false,
		"icon": "ExtResource( 2 )",
		"show_item": true,
		"show_scene": false,
		"uses_size": true,
		"action": "",
		"action_params": [],
		"release_action": "",
		"prop_code": "",
		"help_text": "",
		"arm_value": 0.2,
		"hold_offset": 0.0,
		"unselectable": false,
		"category": "fish",
		"alive": true,
		"tier": 1,
		"catch_difficulty": 3.5,
		"catch_speed": 120.0,
		"loot_table": "ocean",
		"loot_weight": 0.5,
		"average_size": 30.0,
		"sell_value": 30,
		"obtain_xp": 60,
		"generate_worth": true,
		"can_be_sold": true,
		"show_bait": false,
		"detect_item": false,
		"item_name": "Lionfish"
	},
	"Lobster": {
		"script": "ExtResource( 1 )",
		"item_description": "Homarus americanus",
		"catch_blurb": "What a beaut!",
		"item_is_hidden": false,
		"icon": "ExtResource( 2 )",
		"show_item": true,
		"show_scene": false,
		"uses_size": true,
		"action": "",
		"action_params": [],
		"release_action": "",
		"prop_code": "",
		"help_text": "",
		"arm_value": 0.2,
		"hold_offset": 0.0,
		"unselectable": false,
		"category": "fish",
		"alive": true,
		"tier": 0,
		"catch_difficulty": 1.5,
		"catch_speed": 120.0,
		"loot_table": "ocean",
		"loot_weight": 0.7,
		"average_size": 75.0,
		"sell_value": 12,
		"obtain_xp": 30,
		"can_be_sold": true,
		"show_bait": false,
		"item_name": "Lobster"
	},
	"Man O' War": {
		"script": "ExtResource( 1 )",
		"item_description": "Physalia physalis",
		"catch_blurb": "ok you should probably not be holding this",
		"item_is_hidden": false,
		"icon": "ExtResource( 2 )",
		"show_item": true,
		"show_scene": false,
		"uses_size": true,
		"action": "",
		"action_params": [],
		"release_action": "",
		"prop_code": "",
		"help_text": "",
		"arm_value": 0.2,
		"hold_offset": 0.0,
		"unselectable": false,
		"category": "fish",
		"alive": true,
		"tier": 2,
		"catch_difficulty": 4.5,
		"catch_speed": 120.0,
		"loot_table": "ocean",
		"loot_weight": 0.2,
		"average_size": 35.0,
		"sell_value": 30,
		"obtain_xp": 60,
		"generate_worth": true,
		"can_be_sold": true,
		"show_bait": false,
		"detect_item": false,
		"item_name": "Man O' War"
	},
	"Manta Ray": {
		"script": "ExtResource( 1 )",
		"item_description": "Mobula birostris",
		"catch_blurb": "The butterfly of the sea!",
		"item_is_hidden": false,
		"icon": "ExtResource( 2 )",
		"show_item": true,
		"show_scene": false,
		"uses_size": true,
		"action": "",
		"action_params": [],
		"release_action": "",
		"prop_code": "",
		"help_text": "",
		"arm_value": 0.2,
		"hold_offset": 0.0,
		"unselectable": false,
		"category": "fish",
		"alive": true,
		"tier": 2,
		"catch_difficulty": 5.0,
		"catch_speed": 120.0,
		"loot_table": "ocean",
		"loot_weight": 0.18,
		"average_size": 600.0,
		"sell_value": 30,
		"sell_multiplier": 1.0,
		"obtain_xp": 60,
		"generate_worth": true,
		"can_be_sold": true,
		"show_bait": false,
		"detect_item": false,
		"item_name": "Manta Ray"
	},
	"Marlin": {
		"script": "ExtResource( 1 )",
		"item_description": "Makaira nigricans",
		"catch_blurb": "Something something MARLIN",
		"item_is_hidden": false,
		"icon": "ExtResource( 2 )",
		"show_item": true,
		"show_scene": false,
		"uses_size": true,
		"action": "",
		"action_params": [],
		"release_action": "",
		"prop_code": "",
		"help_text": "",
		"arm_value": 0.2,
		"hold_offset": 0.0,
		"unselectable": false,
		"category": "fish",
		"alive": true,
		"tier": 1,
		"catch_difficulty": 3.0,
		"catch_speed": 120.0,
		"loot_table": "ocean",
		"loot_weight": 0.6,
		"average_size": 250.0,
		"sell_value": 30,
		"obtain_xp": 60,
		"generate_worth": true,
		"can_be_sold": true,
		"show_bait": false,
		"detect_item": false,
		"item_name": "Marlin"
	},
	"Monocle Fragment": {
		"script": "ExtResource( 1 )",
		"item_description": "Shiny!",
		"catch_blurb": "Woah! Wonder if anyone wants this...",
		"item_is_hidden": false,
		"icon": "ExtResource( 2 )",
		"show_item": true,
		"show_scene": false,
		"uses_size": true,
		"action": "",
		"action_params": [],
		"release_action": "",
		"prop_code": "",
		"help_text": "",
		"arm_value": 0.2,
		"hold_offset": 0.0,
		"unselectable": false,
		"category": "fish",
		"alive": false,
		"tier": 0,
		"catch_difficulty": 1.0,
		"catch_speed": 120.0,
		"loot_table": "metal",
		"loot_weight": 0.18,
		"average_size": 8.0,
		"sell_value": 50,
		"obtain_xp": 30,
		"generate_worth": false,
		"can_be_sold": true,
		"show_bait": false,
		"detect_item": false,
		"item_name": "Monocle Fragment"
	},
	"Mooneye": {
		"script": "ExtResource( 1 )",
		"item_description": "Hiodon tergisus",
		"catch_blurb": "Mooneye? At this time?",
		"item_is_hidden": false,
		"icon": "ExtResource( 2 )",
		"show_item": true,
		"show_scene": false,
		"uses_size": true,
		"action": "",
		"action_params": [],
		"release_action": "",
		"prop_code": "",
		"help_text": "",
		"arm_value": 0.2,
		"hold_offset": 0.0,
		"unselectable": false,
		"category": "fish",
		"alive": true,
		"tier": 2,
		"catch_difficulty": 4.2,
		"catch_speed": 120.0,
		"loot_table": "lake",
		"loot_weight": 0.14,
		"average_size": 30.0,
		"sell_value": 80,
		"obtain_xp": 80,
		"generate_worth": true,
		"can_be_sold": true,
		"show_bait": false,
		"detect_item": false,
		"item_name": "Mooneye"
	},
	"Muskellunge": {
		"script": "ExtResource( 1 )",
		"item_description": "Esox masquinongy",
		"catch_blurb": "A muskie!",
		"item_is_hidden": false,
		"icon": "ExtResource( 2 )",
		"show_item": true,
		"show_scene": false,
		"uses_size": true,
		"action": "",
		"action_params": [],
		"release_action": "",
		"prop_code": "",
		"help_text": "",
		"arm_value": 0.2,
		"hold_offset": 0.0,
		"unselectable": false,
		"category": "fish",
		"alive": true,
		"tier": 1,
		"catch_difficulty": 3.3,
		"catch_speed": 120.0,
		"loot_table": "lake",
		"loot_weight": 0.15,
		"average_size": 100.0,
		"sell_value": 60,
		"obtain_xp": 75,
		"generate_worth": true,
		"can_be_sold": true,
		"show_bait": false,
		"detect_item": false,
		"item_name": "Muskellunge"
	},
	"Octopus": {
		"script": "ExtResource( 1 )",
		"item_description": "Octopus vulgaris",
		"catch_blurb": "How vulgar!",
		"item_is_hidden": false,
		"icon": "ExtResource( 2 )",
		"show_item": true,
		"show_scene": false,
		"uses_size": true,
		"action": "",
		"action_params": [],
		"release_action": "",
		"prop_code": "",
		"help_text": "",
		"arm_value": 0.2,
		"hold_offset": 0.0,
		"unselectable": false,
		"category": "fish",
		"alive": true,
		"tier": 1,
		"catch_difficulty": 3.0,
		"catch_speed": 120.0,
		"loot_table": "ocean",
		"loot_weight": 0.6,
		"average_size": 100.0,
		"sell_value": 30,
		"obtain_xp": 60,
		"generate_worth": true,
		"can_be_sold": true,
		"show_bait": false,
		"detect_item": false,
		"item_name": "Octopus"
	},
	"Old Boot": {
		"script": "ExtResource( 1 )",
		"item_description": "Don't Litter!",
		"catch_blurb": "Yuck! Who put this in here...",
		"item_is_hidden": false,
		"icon": "ExtResource( 2 )",
		"show_item": true,
		"show_scene": false,
		"uses_size": true,
		"action": "",
		"action_params": [],
		"release_action": "",
		"prop_code": "",
		"help_text": "",
		"arm_value": 0.2,
		"hold_offset": 0.0,
		"unselectable": false,
		"category": "fish",
		"alive": false,
		"tier": 0,
		"catch_difficulty": 1.0,
		"catch_speed": 120.0,
		"loot_table": "water_trash",
		"loot_weight": 0.5,
		"average_size": 14.0,
		"sell_value": 15,
		"obtain_xp": 30,
		"generate_worth": false,
		"can_be_sold": true,
		"show_bait": false,
		"detect_item": false,
		"item_name": "Old Boot"
	},
	"Old Coin": {
		"script": "ExtResource( 1 )",
		"item_description": "Filthy...",
		"catch_blurb": "Slightly aged coin means... slightly aged value?",
		"item_is_hidden": false,
		"icon": "ExtResource( 2 )",
		"show_item": true,
		"show_scene": false,
		"uses_size": true,
		"action": "",
		"action_params": [],
		"release_action": "",
		"prop_code": "",
		"help_text": "",
		"arm_value": 0.2,
		"hold_offset": 0.0,
		"unselectable": false,
		"category": "fish",
		"alive": false,
		"tier": 0,
		"catch_difficulty": 1.0,
		"catch_speed": 120.0,
		"loot_table": "metal",
		"loot_weight": 1.0,
		"average_size": 8.0,
		"sell_value": 5,
		"obtain_xp": 30,
		"generate_worth": false,
		"can_be_sold": true,
		"show_bait": false,
		"detect_item": false,
		"item_name": "Old Coin"
	},
	"Oyster": {
		"script": "ExtResource( 1 )",
		"item_description": "Crassostrea gigas",
		"catch_blurb": "Oyster? I hardly know 'er!",
		"item_is_hidden": false,
		"icon": "ExtResource( 2 )",
		"show_item": true,
		"show_scene": false,
		"uses_size": true,
		"action": "",
		"action_params": [],
		"release_action": "",
		"help_text": "",
		"arm_value": 0.2,
		"hold_offset": 0.0,
		"unselectable": false,
		"category": "fish",
		"alive": true,
		"tier": 0,
		"catch_difficulty": 1.5,
		"catch_speed": 120.0,
		"loot_table": "ocean",
		"loot_weight": 0.8,
		"average_size": 18.0,
		"sell_value": 10,
		"obtain_xp": 30,
		"can_be_sold": true,
		"show_bait": false,
		"item_name": "Oyster"
	},
	"Perch": {
		"script": "ExtResource( 1 )",
		"item_description": "Perca flavescens",
		"catch_blurb": "Man am I parched...",
		"item_is_hidden": false,
		"icon": "ExtResource( 2 )",
		"show_item": true,
		"show_scene": false,
		"uses_size": true,
		"action": "",
		"action_params": [],
		"release_action": "",
		"prop_code": "",
		"help_text": "",
		"arm_value": 0.2,
		"hold_offset": 0.0,
		"unselectable": false,
		"category": "fish",
		"alive": true,
		"tier": 0,
		"catch_difficulty": 1.4,
		"catch_speed": 120.0,
		"loot_table": "lake",
		"loot_weight": 1.15,
		"average_size": 20.0,
		"sell_value": 7,
		"obtain_xp": 30,
		"generate_worth": true,
		"can_be_sold": true,
		"show_bait": false,
		"detect_item": false,
		"item_name": "Perch"
	},
	"Pike": {
		"script": "ExtResource( 1 )",
		"item_description": "Esox lucius",
		"catch_blurb": "This Piked my interest!",
		"item_is_hidden": false,
		"icon": "ExtResource( 2 )",
		"show_item": true,
		"show_scene": false,
		"uses_size": true,
		"action": "",
		"action_params": [],
		"release_action": "",
		"prop_code": "",
		"help_text": "",
		"arm_value": 0.2,
		"hold_offset": 0.0,
		"unselectable": false,
		"category": "fish",
		"alive": true,
		"tier": 1,
		"catch_difficulty": 3.0,
		"catch_speed": 120.0,
		"loot_table": "lake",
		"loot_weight": 0.5,
		"average_size": 55.0,
		"sell_value": 25,
		"obtain_xp": 50,
		"generate_worth": true,
		"can_be_sold": true,
		"show_bait": false,
		"detect_item": false,
		"item_name": "Pike"
	},
	"Plastic Bag": {
		"script": "ExtResource( 1 )",
		"item_description": "Don't Litter!",
		"catch_blurb": "Yuck! Who put this in here...",
		"item_is_hidden": false,
		"icon": "ExtResource( 2 )",
		"show_item": true,
		"show_scene": false,
		"uses_size": true,
		"action": "",
		"action_params": [],
		"release_action": "",
		"prop_code": "",
		"help_text": "",
		"arm_value": 0.2,
		"hold_offset": 0.0,
		"unselectable": false,
		"category": "fish",
		"alive": false,
		"tier": 0,
		"catch_difficulty": 1.0,
		"catch_speed": 120.0,
		"loot_table": "water_trash",
		"loot_weight": 1.0,
		"average_size": 12.0,
		"sell_value": 5,
		"obtain_xp": 30,
		"generate_worth": false,
		"can_be_sold": true,
		"show_bait": false,
		"detect_item": false,
		"item_name": "Plastic Bag"
	},
	"Pupfish": {
		"script": "ExtResource( 1 )",
		"item_description": "Cyprinodon pachycephalus",
		"catch_blurb": "A little puppy!",
		"item_is_hidden": false,
		"icon": "ExtResource( 2 )",
		"show_item": true,
		"show_scene": false,
		"uses_size": true,
		"action": "",
		"action_params": [],
		"release_action": "",
		"prop_code": "",
		"help_text": "",
		"arm_value": 0.2,
		"hold_offset": 0.0,
		"unselectable": false,
		"category": "fish",
		"alive": true,
		"tier": 2,
		"catch_difficulty": 3.8,
		"catch_speed": 120.0,
		"loot_table": "lake",
		"loot_weight": 0.14,
		"average_size": 7.0,
		"sell_value": 80,
		"obtain_xp": 80,
		"generate_worth": true,
		"can_be_sold": true,
		"show_bait": false,
		"detect_item": false,
		"item_name": "Pupfish"
	},
	"Rainbow Trout": {
		"script": "ExtResource( 1 )",
		"item_description": "Oncorhynchus mykiss",
		"catch_blurb": "These fishes gay. Good for them, good for them.",
		"item_is_hidden": false,
		"icon": "ExtResource( 2 )",
		"show_item": true,
		"show_scene": false,
		"uses_size": true,
		"action": "",
		"action_params": [],
		"release_action": "",
		"prop_code": "",
		"help_text": "",
		"arm_value": 0.2,
		"hold_offset": 0.0,
		"unselectable": false,
		"category": "fish",
		"alive": true,
		"tier": 0,
		"catch_difficulty": 1.5,
		"catch_speed": 120.0,
		"loot_table": "lake",
		"loot_weight": 1.25,
		"average_size": 60.0,
		"sell_value": 7,
		"obtain_xp": 35,
		"generate_worth": true,
		"can_be_sold": true,
		"show_bait": false,
		"detect_item": false,
		"item_name": "Rainbow Trout"
	},
	"Rusted Ring": {
		"script": "ExtResource( 1 )",
		"item_description": "What a story...",
		"catch_blurb": "Fancy! (Er, well... it USED to be!)",
		"item_is_hidden": false,
		"icon": "ExtResource( 2 )",
		"show_item": true,
		"show_scene": false,
		"uses_size": true,
		"action": "",
		"action_params": [],
		"release_action": "",
		"prop_code": "",
		"help_text": "",
		"arm_value": 0.2,
		"hold_offset": 0.0,
		"unselectable": false,
		"category": "fish",
		"alive": false,
		"tier": 0,
		"catch_difficulty": 1.0,
		"catch_speed": 120.0,
		"loot_table": "metal",
		"loot_weight": 0.2,
		"average_size": 8.0,
		"sell_value": 45,
		"obtain_xp": 30,
		"generate_worth": false,
		"can_be_sold": true,
		"show_bait": false,
		"detect_item": false,
		"item_name": "Rusted Ring"
	},
	"Salmon": {
		"script": "ExtResource( 1 )",
		"item_description": "Oncorhynchus nerka",
		"catch_blurb": "It's Sal' good, 'mon!",
		"item_is_hidden": false,
		"icon": "ExtResource( 2 )",
		"show_item": true,
		"show_scene": false,
		"uses_size": true,
		"action": "",
		"action_params": [],
		"release_action": "",
		"prop_code": "",
		"help_text": "",
		"arm_value": 0.2,
		"hold_offset": 0.0,
		"unselectable": false,
		"category": "fish",
		"alive": true,
		"tier": 0,
		"catch_difficulty": 1.0,
		"catch_speed": 120.0,
		"loot_table": "lake",
		"loot_weight": 1.5,
		"average_size": 70.0,
		"sell_value": 5,
		"obtain_xp": 25,
		"generate_worth": true,
		"can_be_sold": true,
		"show_bait": false,
		"detect_item": false,
		"item_name": "Salmon"
	},
	"Sawfish": {
		"script": "ExtResource( 1 )",
		"item_description": "Pristis perotteti",
		"catch_blurb": "I saw it!",
		"item_is_hidden": false,
		"icon": "ExtResource( 2 )",
		"show_item": true,
		"show_scene": false,
		"uses_size": true,
		"action": "",
		"action_params": [],
		"release_action": "",
		"prop_code": "",
		"help_text": "",
		"arm_value": 0.2,
		"hold_offset": 0.0,
		"unselectable": false,
		"category": "fish",
		"alive": true,
		"tier": 0,
		"catch_difficulty": 4.0,
		"catch_speed": 120.0,
		"loot_table": "ocean",
		"loot_weight": 0.15,
		"average_size": 250.0,
		"sell_value": 55,
		"obtain_xp": 100,
		"can_be_sold": true,
		"show_bait": false,
		"item_name": "Sawfish"
	},
	"Sea Turtle": {
		"script": "ExtResource( 1 )",
		"item_description": "Chelonia mydas",
		"catch_blurb": "Surf's up!",
		"item_is_hidden": false,
		"icon": "ExtResource( 2 )",
		"show_item": true,
		"show_scene": false,
		"uses_size": true,
		"action": "",
		"action_params": [],
		"release_action": "",
		"prop_code": "",
		"help_text": "",
		"arm_value": 0.2,
		"hold_offset": 0.0,
		"unselectable": false,
		"category": "fish",
		"alive": true,
		"tier": 2,
		"catch_difficulty": 4.0,
		"catch_speed": 120.0,
		"loot_table": "ocean",
		"loot_weight": 0.25,
		"average_size": 100.0,
		"sell_value": 30,
		"obtain_xp": 60,
		"generate_worth": true,
		"can_be_sold": true,
		"show_bait": false,
		"detect_item": false,
		"item_name": "Sea Turtle"
	},
	"Seahorse": {
		"script": "ExtResource( 1 )",
		"item_description": "Hippocampus kuda",
		"catch_blurb": "Giddy up!",
		"item_is_hidden": false,
		"icon": "ExtResource( 2 )",
		"show_item": true,
		"show_scene": false,
		"uses_size": true,
		"action": "",
		"action_params": [],
		"release_action": "",
		"prop_code": "",
		"help_text": "",
		"arm_value": 0.2,
		"hold_offset": 0.0,
		"unselectable": false,
		"category": "fish",
		"alive": true,
		"tier": 1,
		"catch_difficulty": 2.5,
		"catch_speed": 120.0,
		"loot_table": "ocean",
		"loot_weight": 0.7,
		"average_size": 25.0,
		"sell_value": 30,
		"obtain_xp": 60,
		"generate_worth": true,
		"can_be_sold": true,
		"show_bait": false,
		"detect_item": false,
		"item_name": "Seahorse"
	},
	"Shrimp": {
		"script": "ExtResource( 1 )",
		"item_description": "Pandalus borealis",
		"catch_blurb": "One in a krillion! (this isnt a krill btw)",
		"item_is_hidden": false,
		"icon": "ExtResource( 2 )",
		"show_item": true,
		"show_scene": false,
		"uses_size": true,
		"action": "",
		"action_params": [],
		"release_action": "",
		"prop_code": "",
		"help_text": "",
		"arm_value": 0.2,
		"hold_offset": 0.0,
		"unselectable": false,
		"category": "fish",
		"alive": true,
		"tier": 0,
		"catch_difficulty": 1.2,
		"catch_speed": 120.0,
		"loot_table": "ocean",
		"loot_weight": 1.0,
		"average_size": 15.0,
		"sell_value": 9,
		"obtain_xp": 35,
		"can_be_sold": true,
		"show_bait": false,
		"item_name": "Shrimp"
	},
	"Snail": {
		"script": "ExtResource( 1 )",
		"item_description": "Lymnaea stagnalis",
		"catch_blurb": "Meow?",
		"item_is_hidden": false,
		"icon": "ExtResource( 2 )",
		"show_item": true,
		"show_scene": false,
		"uses_size": true,
		"action": "",
		"action_params": [],
		"release_action": "",
		"prop_code": "",
		"help_text": "",
		"arm_value": 0.2,
		"hold_offset": 0.0,
		"unselectable": false,
		"category": "fish",
		"alive": true,
		"tier": 0,
		"catch_difficulty": 1.0,
		"catch_speed": 120.0,
		"loot_table": "lake",
		"loot_weight": 0.6,
		"average_size": 4.0,
		"sell_value": 20,
		"obtain_xp": 40,
		"generate_worth": true,
		"can_be_sold": true,
		"show_bait": false,
		"detect_item": false,
		"item_name": "Snail"
	},
	"Soda Can": {
		"script": "ExtResource( 1 )",
		"item_description": "Don't Litter!",
		"catch_blurb": "Yuck! Who put this in here...",
		"item_is_hidden": false,
		"icon": "ExtResource( 2 )",
		"show_item": true,
		"show_scene": false,
		"uses_size": true,
		"action": "",
		"action_params": [],
		"release_action": "",
		"prop_code": "",
		"help_text": "",
		"arm_value": 0.2,
		"hold_offset": 0.0,
		"unselectable": false,
		"category": "fish",
		"alive": false,
		"tier": 0,
		"catch_difficulty": 1.0,
		"catch_speed": 120.0,
		"loot_table": "water_trash",
		"loot_weight": 1.0,
		"average_size": 3.0,
		"sell_value": 5,
		"obtain_xp": 30,
		"generate_worth": false,
		"can_be_sold": true,
		"show_bait": false,
		"detect_item": false,
		"item_name": "Soda Can"
	},
	"Soda Tab": {
		"script": "ExtResource( 1 )",
		"item_description": "Filthy...",
		"catch_blurb": "Not the most interesting find, for sure...",
		"item_is_hidden": false,
		"icon": "ExtResource( 2 )",
		"show_item": true,
		"show_scene": false,
		"uses_size": true,
		"action": "",
		"action_params": [],
		"release_action": "",
		"prop_code": "",
		"help_text": "",
		"arm_value": 0.2,
		"hold_offset": 0.0,
		"unselectable": false,
		"category": "fish",
		"alive": false,
		"tier": 0,
		"catch_difficulty": 1.0,
		"catch_speed": 120.0,
		"loot_table": "metal",
		"loot_weight": 1.0,
		"average_size": 8.0,
		"sell_value": 8,
		"obtain_xp": 30,
		"generate_worth": false,
		"can_be_sold": true,
		"show_bait": false,
		"detect_item": false,
		"item_name": "Soda Tab"
	},
	"Squid": {
		"script": "ExtResource( 1 )",
		"item_description": "Dosidicus gigas",
		"catch_blurb": "A true alien!",
		"item_is_hidden": false,
		"icon": "ExtResource( 2 )",
		"show_item": true,
		"show_scene": false,
		"uses_size": true,
		"action": "",
		"action_params": [],
		"release_action": "",
		"prop_code": "",
		"help_text": "",
		"arm_value": 0.2,
		"hold_offset": 0.0,
		"unselectable": false,
		"category": "fish",
		"alive": true,
		"tier": 2,
		"catch_difficulty": 4.4,
		"catch_speed": 120.0,
		"loot_table": "ocean",
		"loot_weight": 0.25,
		"average_size": 230.0,
		"sell_value": 30,
		"obtain_xp": 60,
		"generate_worth": true,
		"can_be_sold": true,
		"show_bait": false,
		"detect_item": false,
		"item_name": "Squid"
	},
	"Sting Ray": {
		"script": "ExtResource( 1 )",
		"item_description": "Dasyatis pastinaca",
		"catch_blurb": "What a ripper!",
		"item_is_hidden": false,
		"icon": "ExtResource( 2 )",
		"show_item": true,
		"show_scene": false,
		"uses_size": true,
		"action": "",
		"action_params": [],
		"release_action": "",
		"prop_code": "",
		"help_text": "",
		"arm_value": 0.2,
		"hold_offset": 0.0,
		"unselectable": false,
		"category": "fish",
		"alive": true,
		"tier": 1,
		"catch_difficulty": 3.0,
		"catch_speed": 120.0,
		"loot_table": "ocean",
		"loot_weight": 0.6,
		"average_size": 150.0,
		"sell_value": 30,
		"obtain_xp": 60,
		"generate_worth": true,
		"can_be_sold": true,
		"show_bait": false,
		"detect_item": false,
		"item_name": "Sting Ray"
	},
	"Sturgeon": {
		"script": "ExtResource( 1 )",
		"item_description": "Acipenser fulvescens",
		"catch_blurb": "I want a second opinion.",
		"item_is_hidden": false,
		"icon": "ExtResource( 2 )",
		"show_item": true,
		"show_scene": false,
		"uses_size": true,
		"action": "",
		"action_params": [],
		"release_action": "",
		"prop_code": "",
		"help_text": "",
		"arm_value": 0.2,
		"hold_offset": 0.0,
		"unselectable": false,
		"category": "fish",
		"alive": true,
		"tier": 0,
		"catch_difficulty": 2.2,
		"catch_speed": 120.0,
		"loot_table": "lake",
		"loot_weight": 0.2,
		"average_size": 150.0,
		"sell_value": 40,
		"obtain_xp": 60,
		"generate_worth": true,
		"can_be_sold": true,
		"show_bait": false,
		"detect_item": false,
		"item_name": "Sturgeon"
	},
	"Sunfish": {
		"script": "ExtResource( 1 )",
		"item_description": "Mola mola",
		"catch_blurb": "Here it comes!",
		"item_is_hidden": false,
		"icon": "ExtResource( 2 )",
		"show_item": true,
		"show_scene": false,
		"uses_size": true,
		"action": "",
		"action_params": [],
		"release_action": "",
		"help_text": "",
		"arm_value": 0.2,
		"hold_offset": 0.0,
		"unselectable": false,
		"category": "fish",
		"alive": true,
		"tier": 0,
		"catch_difficulty": 3.0,
		"catch_speed": 120.0,
		"loot_table": "ocean",
		"loot_weight": 0.4,
		"average_size": 190.0,
		"sell_value": 30,
		"obtain_xp": 70,
		"can_be_sold": true,
		"show_bait": false,
		"item_name": "Sunfish"
	},
	"Swordfish": {
		"script": "ExtResource( 1 )",
		"item_description": "Xiphias gladius",
		"catch_blurb": "Master duelist!",
		"item_is_hidden": false,
		"icon": "ExtResource( 2 )",
		"show_item": true,
		"show_scene": false,
		"uses_size": true,
		"action": "",
		"action_params": [],
		"release_action": "",
		"prop_code": "",
		"help_text": "",
		"arm_value": 0.2,
		"hold_offset": 0.0,
		"unselectable": false,
		"category": "fish",
		"alive": true,
		"tier": 1,
		"catch_difficulty": 3.0,
		"catch_speed": 120.0,
		"loot_table": "ocean",
		"loot_weight": 0.65,
		"average_size": 280.0,
		"sell_value": 30,
		"obtain_xp": 60,
		"generate_worth": true,
		"can_be_sold": true,
		"show_bait": false,
		"detect_item": false,
		"item_name": "Swordfish"
	},
	"Toad": {
		"script": "ExtResource( 1 )",
		"item_description": "Bufo bufo",
		"catch_blurb": "What a boy!",
		"item_is_hidden": false,
		"icon": "ExtResource( 2 )",
		"show_item": true,
		"show_scene": false,
		"uses_size": true,
		"action": "",
		"action_params": [],
		"release_action": "",
		"prop_code": "",
		"help_text": "",
		"arm_value": 0.2,
		"hold_offset": 0.0,
		"unselectable": false,
		"category": "fish",
		"alive": true,
		"tier": 1,
		"catch_difficulty": 2.5,
		"catch_speed": 120.0,
		"loot_table": "lake",
		"loot_weight": 0.35,
		"average_size": 10.0,
		"sell_value": 30,
		"obtain_xp": 60,
		"generate_worth": true,
		"can_be_sold": true,
		"show_bait": false,
		"detect_item": false,
		"item_name": "Toad"
	},
	"Tuna": {
		"script": "ExtResource( 1 )",
		"item_description": "Thunnus alalunga",
		"catch_blurb": "Well this was a tuna fun!",
		"item_is_hidden": false,
		"icon": "ExtResource( 2 )",
		"show_item": true,
		"show_scene": false,
		"uses_size": true,
		"action": "",
		"action_params": [],
		"release_action": "",
		"prop_code": "",
		"help_text": "",
		"arm_value": 0.2,
		"hold_offset": 0.0,
		"unselectable": false,
		"category": "fish",
		"alive": true,
		"tier": 0,
		"catch_difficulty": 2.5,
		"catch_speed": 120.0,
		"loot_table": "ocean",
		"loot_weight": 0.7,
		"average_size": 150.0,
		"sell_value": 20,
		"obtain_xp": 60,
		"generate_worth": true,
		"can_be_sold": true,
		"show_bait": false,
		"detect_item": false,
		"item_name": "Tuna"
	},
	"Turtle": {
		"script": "ExtResource( 1 )",
		"item_description": "Actinemys marmorata",
		"catch_blurb": "This catch was quite the hurdle!",
		"item_is_hidden": false,
		"icon": "ExtResource( 2 )",
		"show_item": true,
		"show_scene": false,
		"uses_size": true,
		"action": "",
		"action_params": [],
		"release_action": "",
		"prop_code": "",
		"help_text": "",
		"arm_value": 0.2,
		"hold_offset": 0.0,
		"unselectable": false,
		"category": "fish",
		"alive": true,
		"tier": 1,
		"catch_difficulty": 2.5,
		"catch_speed": 120.0,
		"loot_table": "lake",
		"loot_weight": 0.35,
		"average_size": 24.0,
		"sell_value": 30,
		"obtain_xp": 60,
		"generate_worth": true,
		"can_be_sold": true,
		"show_bait": false,
		"detect_item": false,
		"item_name": "Turtle"
	},
	"Unidentified Fish Object": {
		"script": "ExtResource( 1 )",
		"item_description": "Alienus Caninus",
		"catch_blurb": "...what? the fuck?",
		"item_is_hidden": false,
		"icon": "ExtResource( 2 )",
		"show_item": true,
		"show_scene": false,
		"uses_size": true,
		"action": "",
		"action_params": [],
		"release_action": "",
		"prop_code": "",
		"help_text": "",
		"arm_value": 0.2,
		"hold_offset": 0.0,
		"unselectable": false,
		"category": "fish",
		"alive": true,
		"tier": 1,
		"catch_difficulty": 5.0,
		"catch_speed": 120.0,
		"loot_table": "alien",
		"loot_weight": 1.0,
		"average_size": 90.0,
		"sell_value": 80,
		"obtain_xp": 150,
		"generate_worth": false,
		"can_be_sold": true,
		"show_bait": false,
		"detect_item": false,
		"item_name": "Unidentified Fish Object"
	},
	"Walleye": {
		"script": "ExtResource( 1 )",
		"item_description": "Sander vitreus",
		"catch_blurb": "Walleye? What a guy!",
		"item_is_hidden": false,
		"icon": "ExtResource( 2 )",
		"show_item": true,
		"show_scene": false,
		"uses_size": true,
		"action": "",
		"action_params": [],
		"release_action": "",
		"prop_code": "",
		"help_text": "",
		"arm_value": 0.2,
		"hold_offset": 0.0,
		"unselectable": false,
		"category": "fish",
		"alive": true,
		"tier": 0,
		"catch_difficulty": 1.75,
		"catch_speed": 120.0,
		"loot_table": "lake",
		"loot_weight": 1.15,
		"average_size": 70.0,
		"sell_value": 9,
		"obtain_xp": 40,
		"generate_worth": true,
		"can_be_sold": true,
		"show_bait": false,
		"detect_item": false,
		"item_name": "Walleye"
	},
	"Watch Fragment": {
		"script": "ExtResource( 1 )",
		"item_description": "Shiny!",
		"catch_blurb": "Woah! Wonder if anyone wants this...",
		"item_is_hidden": false,
		"icon": "ExtResource( 2 )",
		"show_item": true,
		"show_scene": false,
		"uses_size": true,
		"action": "",
		"action_params": [],
		"release_action": "",
		"prop_code": "",
		"help_text": "",
		"arm_value": 0.2,
		"hold_offset": 0.0,
		"unselectable": false,
		"category": "fish",
		"alive": false,
		"tier": 0,
		"catch_difficulty": 1.0,
		"catch_speed": 120.0,
		"loot_table": "metal",
		"loot_weight": 0.18,
		"average_size": 8.0,
		"sell_value": 50,
		"obtain_xp": 30,
		"generate_worth": false,
		"can_be_sold": true,
		"show_bait": false,
		"detect_item": false,
		"item_name": "Watch Fragment"
	},
	"Weed": {
		"script": "ExtResource( 1 )",
		"item_description": "Weed!",
		"catch_blurb": "Agh! Caught a snag!",
		"item_is_hidden": false,
		"icon": "ExtResource( 2 )",
		"show_item": true,
		"show_scene": false,
		"uses_size": true,
		"action": "",
		"action_params": [],
		"release_action": "",
		"prop_code": "",
		"help_text": "",
		"arm_value": 0.2,
		"hold_offset": 0.0,
		"unselectable": false,
		"category": "fish",
		"alive": false,
		"tier": 0,
		"catch_difficulty": 1.0,
		"catch_speed": 120.0,
		"loot_table": "water_trash",
		"loot_weight": 1.0,
		"average_size": 10.0,
		"sell_value": 5,
		"obtain_xp": 30,
		"generate_worth": false,
		"can_be_sold": true,
		"show_bait": false,
		"detect_item": false,
		"item_name": "Weed"
	},
	"Whale": {
		"script": "ExtResource( 1 )",
		"item_description": "Balaenoptera musculus",
		"catch_blurb": "A whale of a time!",
		"item_is_hidden": false,
		"icon": "ExtResource( 2 )",
		"show_item": true,
		"show_scene": false,
		"uses_size": true,
		"action": "",
		"action_params": [],
		"release_action": "",
		"prop_code": "",
		"help_text": "",
		"arm_value": 0.2,
		"hold_offset": 0.0,
		"unselectable": false,
		"category": "fish",
		"alive": true,
		"tier": 2,
		"catch_difficulty": 5.5,
		"catch_speed": 120.0,
		"loot_table": "ocean",
		"loot_weight": 0.11,
		"average_size": 2200.0,
		"sell_value": 30,
		"obtain_xp": 60,
		"generate_worth": true,
		"can_be_sold": true,
		"show_bait": false,
		"detect_item": false,
		"item_name": "Whale"
	},
	"Wolffish": {
		"script": "ExtResource( 1 )",
		"item_description": "Anarhichas lupus",
		"catch_blurb": "A true alpha.",
		"item_is_hidden": false,
		"icon": "ExtResource( 2 )",
		"show_item": true,
		"show_scene": false,
		"uses_size": true,
		"action": "",
		"action_params": [],
		"release_action": "",
		"prop_code": "",
		"help_text": "",
		"arm_value": 0.2,
		"hold_offset": 0.0,
		"unselectable": false,
		"category": "fish",
		"alive": true,
		"tier": 1,
		"catch_difficulty": 4.5,
		"catch_speed": 120.0,
		"loot_table": "ocean",
		"loot_weight": 0.35,
		"average_size": 125.0,
		"sell_value": 30,
		"obtain_xp": 60,
		"generate_worth": true,
		"can_be_sold": true,
		"show_bait": false,
		"detect_item": false,
		"item_name": "Wolffish"
	}
}